dqfit/__init__.py
dqfit/_wip.ipynb
dqfit/constants.py
dqfit/dimensions.py
dqfit/helpers.py
dqfit/io.py
dqfit/model.py
dqfit/population.py
dqfit/snowflake_population.py
dqfit/transform.py
dqfit/visualize.py
dqfit/__pycache__/__init__.cpython-311.pyc
dqfit/__pycache__/constants.cpython-311.pyc
dqfit/__pycache__/dimensions.cpython-311.pyc
dqfit/__pycache__/helpers.cpython-311.pyc
dqfit/__pycache__/io.cpython-311.pyc
dqfit/__pycache__/model.cpython-311.pyc
dqfit/__pycache__/population.cpython-311.pyc
dqfit/__pycache__/transform.cpython-311.pyc
dqfit/__pycache__/visualize.cpython-311.pyc
dqfit/data/context/COLE.json
dqfit/data/context/HEDIS.json
dqfit/data/context/_wip.json
dqfit/data/context/a1c-alt.json
dqfit/data/context/a1c.json
dqfit/data/context/example.json
dqfit/data/context/hello-world.json
dqfit/data/context/patient-equity.json
dqfit/data/context/risk-adjustment.json
dqfit/data/context/systolic.json
dqfit/data/context/uscdi.json
dqfit/data/reference/ucum.json
dqfit/data/synthetic/synthea_1/hello-world-bundle.json
dqfit/data/synthetic/synthea_10/Aaron697_Veum823_f11ade6b-fae3-c20d-0a46-e344db669410.json
dqfit/data/synthetic/synthea_10/Abdul218_Gislason620_81469779-7e7f-4864-6fdc-41e52a68ba80.json
dqfit/data/synthetic/synthea_10/Addie421_Weber641_6d7ea981-c548-3d1e-0b59-ba2acbb149d2.json
dqfit/data/synthetic/synthea_10/Adele475_Barton704_4d604ebf-23a9-7a3f-affe-ec4c69f1644d.json
dqfit/data/synthetic/synthea_10/Adena533_Rice937_3470129b-6f4d-27d6-b25b-65a2903514b6.json
dqfit/data/synthetic/synthea_10/Adina377_Barton704_5bde62b3-df9f-623d-e6f8-bd335bc02dc0.json
dqfit/data/synthetic/synthea_10/Adrian111_Collins926_c9e3828c-7466-5f82-a675-213e088c6e7c.json
dqfit/data/synthetic/synthea_10/Agustin437_Russel238_fc56a4f3-04d6-364a-5131-803138497da1.json
dqfit/data/synthetic/synthea_10/Aida517_Spencer878_87bc62d9-7a08-3ecf-0723-d3d918698e0c.json
dqfit/data/synthetic/synthea_10/Aileen250_Bahringer146_5cc757f3-f20b-e88f-c23e-5faee619e6ac.json
dqfit-0.1.10.dist-info/METADATA
dqfit-0.1.10.dist-info/WHEEL
dqfit-0.1.10.dist-info/top_level.txt
dqfit-0.1.10.dist-info/RECORD
