Metadata-Version: 2.1
Name: dqfit
Version: 0.1.10
Summary: Data Quality Fitness Index Tool
Author: Parker Holcomb
Project-URL: Homepage, https://github.com/clinicalqualitydata/dqfit-python
Requires-Python: >=3.7
Requires-Dist: pandas ~=1.5.3
Requires-Dist: plotly ~=5.13.1
